ai_test_designer/__init__.py
ai_test_designer/ai_test_designer.py
ai_test_designer/ai_test_designer_library.py
ai_test_designer-0.0.1.dist-info/LICENSE
ai_test_designer-0.0.1.dist-info/METADATA
ai_test_designer-0.0.1.dist-info/WHEEL
ai_test_designer-0.0.1.dist-info/entry_points.txt
ai_test_designer-0.0.1.dist-info/top_level.txt
ai_test_designer-0.0.1.dist-info/RECORD
